pyrts/__init__.py
pyrts/server.py
python_microRTS-0.0.1.dist-info/DESCRIPTION.rst
python_microRTS-0.0.1.dist-info/METADATA
python_microRTS-0.0.1.dist-info/RECORD
python_microRTS-0.0.1.dist-info/WHEEL
python_microRTS-0.0.1.dist-info/metadata.json
python_microRTS-0.0.1.dist-info/top_level.txt
